hltb_oracle/__init__.py
hltb_oracle/main.py
hltb_oracle/models.py
hltb_oracle/parser.py
hltb_oracle/website.py
hltb_oracle-0.1.4.dist-info/LICENSE
hltb_oracle-0.1.4.dist-info/WHEEL
hltb_oracle-0.1.4.dist-info/METADATA
hltb_oracle-0.1.4.dist-info/RECORD
